setup.cfg
setup.py
audit_pkg/__init__.py
audit_pkg/__main__.py
audit_pkg.egg-info/PKG-INFO
audit_pkg.egg-info/SOURCES.txt
audit_pkg.egg-info/dependency_links.txt
audit_pkg.egg-info/entry_points.txt
audit_pkg.egg-info/not-zip-safe
audit_pkg.egg-info/top_level.txt
audit_pkg/dist/main
audit_pkg/dist/main.exe