Metadata-Version: 1.0
Name: audit-pkg
Version: 1.5.1
Summary: Package auditors distributions
Home-page: UNKNOWN
Author: Flobert Gantua
Author-email: fgantua32@gmail.com
License: UNKNOWN
Platform: UNKNOWN
